{
  "marketing_stripe": {
    "text": "➡️ Utilize o cupom PRIMEIRACOMPRA no carrinho 🛒",
    "link": "",
    "background": "#482973",
    "color": "#3cb4e7"
  },
  "contacts_stripe": {
    "pages": [
      {
        "title": "Segunda à sexta das 09:00 às 17:00"
      },
      {
        "title": "Entrega para todo Brasil"
      },
      {
        "title": "Blog da Adequim",
        "link": "https://www.adequim.com.br/blog"
      }
    ],
    "phone_wpp": true,
    "socials": true
  },
  "categories_list": {
    "featured": [
      "/antimofo?Antimofo",
      "/impermeabilizantes?Impermeabilizantes",
      "/removedores?Removedores",
      "/mascaras?Máscaras"
    ],
    "random": 0,
    "full_width": false
  },
  "search_input": true,
  "desktop_megamenu": true,
  "alphabetical_order_submenu": true,
  "full_width_submenu": true
}